{"nodes": [{"id": "configuracion_html_configuracion_page", "label": "Page: Configuracion (configuracion.html)", "file_type": "code", "source_file": "frontend/configuracion.html", "source_location": "line 1", "source_url": null, "captured_at": null, "author": null, "contributor": null}], "edges": [{"source": "configuracion_html_configuracion_page", "target": "auth_requireadmin", "relation": "calls", "confidence": "INFERRED", "confidence_score": 0.95, "source_file": "frontend/configuracion.html", "source_location": null, "weight": 0.95}], "hyperedges": []}